pickydict/PickyDict.py
pickydict/__init__.py
pickydict/__version__.py
pickydict-0.5.0.dist-info/LICENSE
pickydict-0.5.0.dist-info/METADATA
pickydict-0.5.0.dist-info/WHEEL
pickydict-0.5.0.dist-info/top_level.txt
pickydict-0.5.0.dist-info/RECORD
