Metadata-Version: 2.1
Name: pickydict
Version: 0.5.0
Summary: More picky version of Python dictionary.
Home-page: https://github.com/florian-huber/pickydict
Author: Florian Huber
Author-email: 
License: MIT
Platform: UNKNOWN
Requires-Python: >=3.8
Provides-Extra: dev
Requires-Dist: prospector[with_pyroma]; extra == "dev"
Requires-Dist: pytest; extra == "dev"
Requires-Dist: pytest-cov; extra == "dev"
